LICENSE
MANIFEST.in
README
setup.py
bin/ligolw_cbc_align_total_spin
bin/ligolw_cbc_cluster_coincs
bin/ligolw_cbc_dbinjfind
bin/ligolw_cbc_hardware_inj_page
bin/ligolw_cbc_jitter_skyloc
bin/ligolw_cbc_plotcumhist
bin/ligolw_cbc_plotfm
bin/ligolw_cbc_plotifar
bin/ligolw_cbc_plotslides
bin/ligolw_cbc_printlc
bin/ligolw_cbc_printmissed
bin/ligolw_cbc_printsims
bin/ligolw_cbc_sstinca
bin/pylal_cbc_cohptf_efficiency
bin/pylal_cbc_cohptf_html_summary
bin/pylal_cbc_cohptf_injcombiner
bin/pylal_cbc_cohptf_injfinder
bin/pylal_cbc_cohptf_inspiral_horizon
bin/pylal_cbc_cohptf_sbv_plotter
bin/pylal_cbc_cohptf_trig_cluster
bin/pylal_cbc_cohptf_trig_combiner
bin/pylal_cbc_minifollowups
bin/pylal_cbc_plotinspiral
bin/pylal_cbc_plotinspiralrange
bin/pylal_cbc_plotnumtemplates
bin/pylal_cbc_sink
bin/pylal_cbc_svim
misc/__init__.py
misc/__init__.pyc
misc/generate_vcs_info.py
misc/generate_vcs_info.pyc
misc/git_version.py.in
pycbc_pylal.egg-info/PKG-INFO
pycbc_pylal.egg-info/SOURCES.txt
pycbc_pylal.egg-info/dependency_links.txt
pycbc_pylal.egg-info/top_level.txt
pylal/CoincInspiralUtils.py
pylal/InspiralUtils.py
pylal/MultiInspiralUtils.py
pylal/SearchSummaryUtils.py
pylal/SimInspiralUtils.py
pylal/SnglInspiralUtils.py
pylal/__init__.py
pylal/antenna.py
pylal/cbc_table_utils.py
pylal/cbc_timeslides.py
pylal/coh_PTF_pyutils.py
pylal/db_thinca_rings.py
pylal/followup_trigger.py
pylal/git_version.py
pylal/grbsummary.py
pylal/imr_utils.py
pylal/inject.py
pylal/legacy_ihope.py
pylal/ligolw_burca2.py
pylal/ligolw_cafe.py
pylal/ligolw_cbc_compute_durations.py
pylal/ligolw_dataUtils.py
pylal/ligolw_dbinjfind.py
pylal/ligolw_inspinjfind.py
pylal/ligolw_sicluster.py
pylal/ligolw_sqlutils.py
pylal/ligolw_sstinca.py
pylal/ligolw_thinca.py
pylal/ligolw_tisi.py
pylal/packing.py
pylal/plotutils.py
pylal/printutils.py
pylal/pygrb_cohptf_pp.py
pylal/rate.py
pylal/series.py
pylal/snglcluster.py
pylal/snglcoinc.py
pylal/spawaveform.py
pylal/sphericalutils.py
pylal/trigger_fits.py
pylal/upper_limit_utils.py
pylal/viz.py
pylal/dq/__init__.py
pylal/dq/dqHTMLUtils.py
pylal/dq/dqSegmentUtils.py
pylal/dq/dqTriggerUtils.py
pylal/xlal/__init__.py
