Metadata-Version: 1.0
Name: pycbc-pylal
Version: 1.0.2
Summary: legacy support python ligo algorithm library
Home-page: https://github.com/ligo-cbc/pycbc-pylal
Author: Ligo Virgo Collaboration - PyCBC team
Author-email: alex.nitz@ligo.org
License: See file LICENSE
Platform: UNKNOWN
